{"cameraMode":{"drawMode":0,"name":"Shaded","section":"Shading Mode"},"sceneLighting":true,"audioPlay":false,"sceneViewState":{"m_AlwaysRefresh":true,"showFog":true,"showSkybox":true,"showFlares":true,"showImageEffects":true,"showParticleSystems":true,"showVisualEffectGraphs":true,"m_FxEnabled":true},"in2DMode":false,"pivot":{"x":-125.63916015625,"y":246.80429077148438,"z":-37.246185302734378},"rotation":{"x":0.16024883091449738,"y":0.2576691508293152,"z":-0.04347330704331398,"w":0.9518718123435974},"size":16.47104263305664,"orthographic":false}